vnpy_xex/__init__.py
vnpy_xex/xex_gateway.py
vnpy_xex-2023.7.5.3.dist-info/LICENSE
vnpy_xex-2023.7.5.3.dist-info/METADATA
vnpy_xex-2023.7.5.3.dist-info/WHEEL
vnpy_xex-2023.7.5.3.dist-info/top_level.txt
vnpy_xex-2023.7.5.3.dist-info/RECORD
